[
 {
  "filename": "MENIBR07.dbc",
  "full_path": "/dissemin/publicos/SINAN/DADOS/FINAIS/MENIBR07.dbc",
  "datetime": "2026-01-22T16:38:00",
  "extension": "dbc",
  "size": 3462196,
  "dataset": "sinan-meni",
  "partition": {
   "uf": "br",
   "year": 2007,
   "month": null,
   "subpartition": null
  },
  "preliminary": false
 },
 {
  "filename": "MENIBR08.dbc",
  "full_path": "/dissemin/publicos/SINAN/DADOS/FINAIS/MENIBR08.dbc",
  "datetime": "2026-01-22T16:38:00",
  "extension": "dbc",
  "size": 2956355,
  "dataset": "sinan-meni",
  "partition": {
   "uf": "br",
   "year": 2008,
   "month": null,
   "subpartition": null
  },
  "preliminary": false
 },
 {
  "filename": "MENIBR09.dbc",
  "full_path": "/dissemin/publicos/SINAN/DADOS/FINAIS/MENIBR09.dbc",
  "datetime": "2026-01-22T16:38:00",
  "extension": "dbc",
  "size": 3043437,
  "dataset": "sinan-meni",
  "partition": {
   "uf": "br",
   "year": 2009,
   "month": null,
   "subpartition": null
  },
  "preliminary": false
 },
 {
  "filename": "MENIBR10.dbc",
  "full_path": "/dissemin/publicos/SINAN/DADOS/FINAIS/MENIBR10.dbc",
  "datetime": "2026-01-22T16:38:00",
  "extension": "dbc",
  "size": 2836851,
  "dataset": "sinan-meni",
  "partition": {
   "uf": "br",
   "year": 2010,
   "month": null,
   "subpartition": null
  },
  "preliminary": false
 },
 {
  "filename": "MENIBR11.dbc",
  "full_path": "/dissemin/publicos/SINAN/DADOS/FINAIS/MENIBR11.dbc",
  "datetime": "2026-01-22T16:38:00",
  "extension": "dbc",
  "size": 2884509,
  "dataset": "sinan-meni",
  "partition": {
   "uf": "br",
   "year": 2011,
   "month": null,
   "subpartition": null
  },
  "preliminary": false
 },
 {
  "filename": "MENIBR12.dbc",
  "full_path": "/dissemin/publicos/SINAN/DADOS/FINAIS/MENIBR12.dbc",
  "datetime": "2026-01-22T16:38:00",
  "extension": "dbc",
  "size": 2852207,
  "dataset": "sinan-meni",
  "partition": {
   "uf": "br",
   "year": 2012,
   "month": null,
   "subpartition": null
  },
  "preliminary": false
 },
 {
  "filename": "MENIBR13.dbc",
  "full_path": "/dissemin/publicos/SINAN/DADOS/FINAIS/MENIBR13.dbc",
  "datetime": "2026-01-22T16:38:00",
  "extension": "dbc",
  "size": 2565318,
  "dataset": "sinan-meni",
  "partition": {
   "uf": "br",
   "year": 2013,
   "month": null,
   "subpartition": null
  },
  "preliminary": false
 },
 {
  "filename": "MENIBR14.dbc",
  "full_path": "/dissemin/publicos/SINAN/DADOS/FINAIS/MENIBR14.dbc",
  "datetime": "2026-01-22T16:38:00",
  "extension": "dbc",
  "size": 2466681,
  "dataset": "sinan-meni",
  "partition": {
   "uf": "br",
   "year": 2014,
   "month": null,
   "subpartition": null
  },
  "preliminary": false
 },
 {
  "filename": "MENIBR15.dbc",
  "full_path": "/dissemin/publicos/SINAN/DADOS/FINAIS/MENIBR15.dbc",
  "datetime": "2026-01-22T16:38:00",
  "extension": "dbc",
  "size": 2291359,
  "dataset": "sinan-meni",
  "partition": {
   "uf": "br",
   "year": 2015,
   "month": null,
   "subpartition": null
  },
  "preliminary": false
 },
 {
  "filename": "MENIBR16.dbc",
  "full_path": "/dissemin/publicos/SINAN/DADOS/FINAIS/MENIBR16.dbc",
  "datetime": "2026-01-22T16:38:00",
  "extension": "dbc",
  "size": 2251685,
  "dataset": "sinan-meni",
  "partition": {
   "uf": "br",
   "year": 2016,
   "month": null,
   "subpartition": null
  },
  "preliminary": false
 },
 {
  "filename": "MENIBR17.dbc",
  "full_path": "/dissemin/publicos/SINAN/DADOS/FINAIS/MENIBR17.dbc",
  "datetime": "2026-01-22T16:38:00",
  "extension": "dbc",
  "size": 2539280,
  "dataset": "sinan-meni",
  "partition": {
   "uf": "br",
   "year": 2017,
   "month": null,
   "subpartition": null
  },
  "preliminary": false
 },
 {
  "filename": "MENIBR18.dbc",
  "full_path": "/dissemin/publicos/SINAN/DADOS/FINAIS/MENIBR18.dbc",
  "datetime": "2026-01-22T16:38:00",
  "extension": "dbc",
  "size": 2487254,
  "dataset": "sinan-meni",
  "partition": {
   "uf": "br",
   "year": 2018,
   "month": null,
   "subpartition": null
  },
  "preliminary": false
 },
 {
  "filename": "MENIBR19.dbc",
  "full_path": "/dissemin/publicos/SINAN/DADOS/FINAIS/MENIBR19.dbc",
  "datetime": "2026-01-22T16:38:00",
  "extension": "dbc",
  "size": 2443227,
  "dataset": "sinan-meni",
  "partition": {
   "uf": "br",
   "year": 2019,
   "month": null,
   "subpartition": null
  },
  "preliminary": false
 },
 {
  "filename": "MENIBR20.dbc",
  "full_path": "/dissemin/publicos/SINAN/DADOS/FINAIS/MENIBR20.dbc",
  "datetime": "2026-01-22T16:38:00",
  "extension": "dbc",
  "size": 1173230,
  "dataset": "sinan-meni",
  "partition": {
   "uf": "br",
   "year": 2020,
   "month": null,
   "subpartition": null
  },
  "preliminary": false
 },
 {
  "filename": "MENIBR21.dbc",
  "full_path": "/dissemin/publicos/SINAN/DADOS/FINAIS/MENIBR21.dbc",
  "datetime": "2026-01-22T16:38:00",
  "extension": "dbc",
  "size": 1194958,
  "dataset": "sinan-meni",
  "partition": {
   "uf": "br",
   "year": 2021,
   "month": null,
   "subpartition": null
  },
  "preliminary": false
 },
 {
  "filename": "MENIBR22.dbc",
  "full_path": "/dissemin/publicos/SINAN/DADOS/FINAIS/MENIBR22.dbc",
  "datetime": "2026-01-22T16:38:00",
  "extension": "dbc",
  "size": 2049386,
  "dataset": "sinan-meni",
  "partition": {
   "uf": "br",
   "year": 2022,
   "month": null,
   "subpartition": null
  },
  "preliminary": false
 },
 {
  "filename": "MENIBR23.dbc",
  "full_path": "/dissemin/publicos/SINAN/DADOS/PRELIM/MENIBR23.dbc",
  "datetime": "2026-01-22T16:39:00",
  "extension": "dbc",
  "size": 2619033,
  "dataset": "sinan-meni",
  "partition": {
   "uf": "br",
   "year": 2023,
   "month": null,
   "subpartition": null
  },
  "preliminary": true
 },
 {
  "filename": "MENIBR24.dbc",
  "full_path": "/dissemin/publicos/SINAN/DADOS/PRELIM/MENIBR24.dbc",
  "datetime": "2026-01-22T09:48:00",
  "extension": "dbc",
  "size": 2546312,
  "dataset": "sinan-meni",
  "partition": {
   "uf": "br",
   "year": 2024,
   "month": null,
   "subpartition": null
  },
  "preliminary": true
 },
 {
  "filename": "MENIBR25.dbc",
  "full_path": "/dissemin/publicos/SINAN/DADOS/PRELIM/MENIBR25.dbc",
  "datetime": "2026-01-22T09:48:00",
  "extension": "dbc",
  "size": 2549711,
  "dataset": "sinan-meni",
  "partition": {
   "uf": "br",
   "year": 2025,
   "month": null,
   "subpartition": null
  },
  "preliminary": true
 },
 {
  "filename": "MENIBR26.dbc",
  "full_path": "/dissemin/publicos/SINAN/DADOS/PRELIM/MENIBR26.dbc",
  "datetime": "2026-01-22T09:48:00",
  "extension": "dbc",
  "size": 33491,
  "dataset": "sinan-meni",
  "partition": {
   "uf": "br",
   "year": 2026,
   "month": null,
   "subpartition": null
  },
  "preliminary": true
 }
]